MANIFEST.in
setup.py
version.txt
knpackage/__init__.py
knpackage/data_cleanup_toolbox.py
knpackage/distributed_computing_utils.py
knpackage/redis_utilities.py
knpackage/toolbox.py
knpackage.egg-info/PKG-INFO
knpackage.egg-info/SOURCES.txt
knpackage.egg-info/dependency_links.txt
knpackage.egg-info/not-zip-safe
knpackage.egg-info/top_level.txt