Metadata-Version: 1.0
Name: knpackage
Version: 0.1.24
Summary: KnowEng toolbox
Home-page: https://github.com/KnowEnG/KnowEnG_Pipelines_Library
Author: KnowEng Dev
Author-email: knowengdev@gmail.com
License: University of Illinois Board of Trustees
Platform: UNKNOWN
